digioAdapter/__init__.py
digioAdapter/__version__.py
digioAdapter/digioclient.py
digioAdapter/entry_points.py
villa_digioadapter_jirawutchayapong-0.0.10.dist-info/LICENSE
villa_digioadapter_jirawutchayapong-0.0.10.dist-info/METADATA
villa_digioadapter_jirawutchayapong-0.0.10.dist-info/WHEEL
villa_digioadapter_jirawutchayapong-0.0.10.dist-info/entry_points.txt
villa_digioadapter_jirawutchayapong-0.0.10.dist-info/top_level.txt
villa_digioadapter_jirawutchayapong-0.0.10.dist-info/RECORD
