Metadata-Version: 2.1
Name: villa-digioadapter-jirawutchayapong
Version: 0.0.10
Summary: calling digio endpoint
Home-page: https://github.com/thanakijwanavit/villaWallet
Author: JC
Author-email: chayapongjirawut@gmail.com
License: Apache 2.0
Keywords: villa digio Adapter
Platform: UNKNOWN
Classifier: Development Status :: 4 - Beta
Classifier: Intended Audience :: Developers
Classifier: Programming Language :: Python :: 3.8
Requires-Python: >=3.6.*
Requires-Dist: requests
Requires-Dist: boto3
